jh_pypi/__init__.py
jh_pypi/mod1.py
jh_pypi-0.1.dist-info/METADATA
jh_pypi-0.1.dist-info/WHEEL
jh_pypi-0.1.dist-info/top_level.txt
jh_pypi-0.1.dist-info/RECORD
