Metadata-Version: 2.1
Name: jh-pypi
Version: 0.1
Summary: upload module test
Home-page: UNKNOWN
Author: jh.kim
Author-email: doorbw@outlook.com
License: UNKNOWN
Keywords: pypi test
Platform: UNKNOWN
Classifier: Programming Language :: Python :: 3
Classifier: Programming Language :: Python :: 3.2
Classifier: Programming Language :: Python :: 3.3
Classifier: Programming Language :: Python :: 3.4
Classifier: Programming Language :: Python :: 3.5
Classifier: Programming Language :: Python :: 3.6
Classifier: Programming Language :: Python :: 3.7
Requires-Python: >=3
